{
    "edges": [
        {
            "shape": "flowingEdge", 
            "source": "('tests/test_stats.py', '(func:16249:(test_pr_lmean:16253))')", 
            "target": "('abydos/stats.py', '(func:12345:(pr_lmean:12349))')", 
            "weight": 4
        }, 
        {
            "shape": "flowingEdge", 
            "source": "('tests/test_stats.py', '(func:7072:(test_cond_pos_pop:7076))')", 
            "target": "('abydos/stats.py', '(func:5339:(cond_pos_pop:5343))')", 
            "weight": 4
        }, 
        {
            "shape": "flowingEdge", 
            "source": "('tests/test_stats.py', '(func:4977:(test_dict:4981))')", 
            "target": "('abydos/stats.py', '(func:4583:(dict:4587))')", 
            "weight": 4
        }
    ], 
    "nodes": [
        {
            "AST Diff": 0, 
            "Profile Diff": false, 
            "id": "('abydos/stats.py', '(func:4583:(dict:4587))')", 
            "md5": "7eddca45043ea76cb6862087d11be806", 
            "weight": 2
        }, 
        {
            "AST Diff": 0, 
            "Profile Diff": false, 
            "id": "('abydos/stats.py', '(func:5339:(cond_pos_pop:5343))')", 
            "md5": "81543ac48245e2576bd7ac8f7f79dec8", 
            "weight": 2
        }, 
        {
            "AST Diff": 0, 
            "Profile Diff": false, 
            "id": "('tests/test_stats.py', '(func:16249:(test_pr_lmean:16253))')", 
            "md5": "a6f2a90f899d45eeef5f451832be8c3d", 
            "weight": 2
        }, 
        {
            "AST Diff": 0, 
            "Profile Diff": false, 
            "id": "('abydos/stats.py', '(func:12345:(pr_lmean:12349))')", 
            "md5": "8beb3e676756dadd5db3a6beffb22774", 
            "weight": 2
        }, 
        {
            "AST Diff": 0, 
            "Profile Diff": false, 
            "id": "('tests/test_stats.py', '(func:7072:(test_cond_pos_pop:7076))')", 
            "md5": "72716e544967cfeeed824a8c4729d3ed", 
            "weight": 2
        }, 
        {
            "AST Diff": 0, 
            "Profile Diff": false, 
            "id": "('tests/test_stats.py', '(func:4977:(test_dict:4981))')", 
            "md5": "13c0af80ba495d0b0216e5717e11d22c", 
            "weight": 2
        }
    ]
}