{
    "edges": [
        {
            "source": "('test/unit/test_collator.py', '(func:4145:(test_functions:4240))')", 
            "target": "('src/gofer/collator.py', '__eq__:118')", 
            "weight": 4
        }, 
        {
            "source": "('test/unit/test_collator.py', '(func:4145:(test_functions:4240))')", 
            "target": "('src/gofer/collator.py', '__functions:81')", 
            "weight": 4
        }, 
        {
            "source": "('test/unit/test_collator.py', '(func:4145:(test_functions:4240))')", 
            "target": "('src/gofer/collator.py', '__init__:28')", 
            "weight": 4
        }, 
        {
            "source": "('test/unit/test_config.py', '(func:12412:(test_init:12416))')", 
            "target": "('src/gofer/config.py', '(func:13171:(__init__:13175))')", 
            "weight": 4
        }, 
        {
            "source": "('test/unit/test_collator.py', '(func:1649:(test_map:1884))')", 
            "target": "('src/gofer/collator.py', '__map:56')", 
            "weight": 4
        }, 
        {
            "source": "('test/unit/test_collator.py', '(func:1649:(test_map:1884))')", 
            "target": "('src/gofer/collator.py', '__init__:28')", 
            "weight": 4
        }, 
        {
            "source": "('test/unit/test_mp.py', '(func:4845:(test_init:4849))')", 
            "target": "('src/gofer/mp.py', '(func:3638:(__init__:3642))')", 
            "weight": 4
        }, 
        {
            "source": "('src/gofer/common.py', '(func:5887:(_fn:5891))')", 
            "target": "('src/gofer/common.py', '(func:4549:(purge:4571))')", 
            "weight": 4
        }, 
        {
            "source": "('test/unit/test_mp.py', '(func:947:(test_init:951))')", 
            "target": "('src/gofer/mp.py', '(func:1089:(__init__:1093))')", 
            "weight": 4
        }, 
        {
            "source": "('test/unit/test_mp.py', '(func:3395:(test_close:3434))')", 
            "target": "('src/gofer/mp.py', '(func:2636:(close:2640))')", 
            "weight": 4
        }, 
        {
            "source": "('test/unit/test_mp.py', '(func:3395:(test_close:3434))')", 
            "target": "('src/gofer/mp.py', '(func:2514:(__init__:2518))')", 
            "weight": 4
        }, 
        {
            "source": "('test/unit/test_config.py', '(func:7052:(test_strict_graph:7089))')", 
            "target": "('src/gofer/config.py', '(func:6665:(graph:6669))')", 
            "weight": 4
        }, 
        {
            "source": "('test/unit/test_config.py', '(func:7052:(test_strict_graph:7089))')", 
            "target": "('src/gofer/config.py', '(func:4761:(__init__:4765))')", 
            "weight": 4
        }, 
        {
            "source": "('src/gofer/rmi/context.py', '(class:Context:765)')", 
            "target": "('src/gofer/common.py', '(func:4351:(__init__:4355))')", 
            "weight": 4
        }, 
        {
            "source": "('test/unit/test_metrics.py', '(func:4359:(test_sizeof_dict:4363))')", 
            "target": "('src/gofer/metrics.py', '(func:3846:(_sizeof:3868))')", 
            "weight": 4
        }, 
        {
            "source": "('src/gofer/config.py', '(func:15196:(__str__:15200))')", 
            "target": "('src/gofer/common.py', '(func:936:(utf8:940))')", 
            "weight": 4
        }, 
        {
            "source": "('test/unit/test_proxy.py', '(func:671:(test_agent_1:711))')", 
            "target": "('src/gofer/common.py', '(func:4125:(__init__:4129))')", 
            "weight": 4
        }, 
        {
            "source": "('test/unit/test_proxy.py', '(func:671:(test_agent_1:711))')", 
            "target": "('src/gofer/proxy.py', '(func:708:(__init__:712))')", 
            "weight": 4
        }, 
        {
            "source": "('test/unit/test_mp.py', '(func:5453:(test_write_read:5457))')", 
            "target": "('src/gofer/mp.py', '(func:2514:(__init__:2518))')", 
            "weight": 4
        }, 
        {
            "source": "('test/unit/test_mp.py', '(func:5453:(test_write_read:5457))')", 
            "target": "('src/gofer/mp.py', '(func:2636:(close:2640))')", 
            "weight": 4
        }, 
        {
            "source": "('test/unit/test_mp.py', '(func:5453:(test_write_read:5457))')", 
            "target": "('src/gofer/mp.py', '(func:4388:(get:4392))')", 
            "weight": 4
        }, 
        {
            "source": "('test/unit/test_mp.py', '(func:5453:(test_write_read:5457))')", 
            "target": "('src/gofer/mp.py', '(func:3172:(put:3176))')", 
            "weight": 4
        }, 
        {
            "source": "('test/unit/test_common.py', '(func:6554:(test_released:6605))')", 
            "target": "('src/gofer/common.py', '(func:5887:(_fn:5891))')", 
            "weight": 4
        }, 
        {
            "source": "('src/gofer/config.py', '(func:12156:(valid_property:12160))')", 
            "target": "('src/gofer/config.py', '(func:13171:(__init__:13175))')", 
            "weight": 4
        }, 
        {
            "source": "('test/unit/test_common.py', '(func:6253:(test_abort:6257))')", 
            "target": "('src/gofer/common.py', '(func:1981:(__init__:1985))')", 
            "weight": 4
        }, 
        {
            "source": "('test/unit/test_config.py', '(func:8585:(ined:8621))')", 
            "target": "('src/gofer/config.py', '(func:8483:(validate:8487))')", 
            "weight": 4
        }, 
        {
            "source": "('test/unit/test_config.py', '(func:8585:(ined:8621))')", 
            "target": "('src/gofer/config.py', '(func:4761:(__init__:4765))')", 
            "weight": 4
        }, 
        {
            "source": "('test/unit/test_config.py', '(func:8585:(ined:8621))')", 
            "target": "('src/gofer/config.py', '(func:8331:(__init__:8335))')", 
            "weight": 4
        }, 
        {
            "source": "('test/unit/test_collator.py', '(func:3790:(test_function:3827))')", 
            "target": "('src/gofer/collator.py', '__init__:28')", 
            "weight": 4
        }, 
        {
            "source": "('test/unit/test_collator.py', '(func:3790:(test_function:3827))')", 
            "target": "('src/gofer/collator.py', '__function:77')", 
            "weight": 4
        }, 
        {
            "source": "('test/unit/test_mp.py', '(func:5972:(test_eof:5976))')", 
            "target": "('src/gofer/mp.py', '(func:2514:(__init__:2518))')", 
            "weight": 4
        }, 
        {
            "source": "('test/unit/test_mp.py', '(func:5972:(test_eof:5976))')", 
            "target": "('src/gofer/mp.py', '(func:2636:(close:2640))')", 
            "weight": 4
        }, 
        {
            "source": "('test/unit/test_config.py', '(func:7276:(test_validate:7317))')", 
            "target": "('src/gofer/config.py', '(func:4761:(__init__:4765))')", 
            "weight": 4
        }, 
        {
            "source": "('test/unit/test_decorators.py', '(func:1224:(test_call:1266))')", 
            "target": "('src/gofer/decorators.py', '(func:1099:(remote:1103))')", 
            "weight": 4
        }, 
        {
            "source": "('test/unit/test_mp.py', '(func:4579:(test_exit:4653))')", 
            "target": "('src/gofer/mp.py', '(func:3409:(__exit__:3413))')", 
            "weight": 4
        }, 
        {
            "source": "('test/unit/test_mp.py', '(func:4579:(test_exit:4653))')", 
            "target": "('src/gofer/mp.py', '(func:2514:(__init__:2518))')", 
            "weight": 4
        }, 
        {
            "source": "('src/gofer/config.py', '(func:19315:(split:19337))')", 
            "target": "('src/gofer/config.py', '(func:18923:(match:18945))')", 
            "weight": 4
        }, 
        {
            "source": "('test/unit/test_mp.py', '(func:1558:(test_start_parent:1620))')", 
            "target": "('src/gofer/mp.py', '(func:1089:(__init__:1093))')", 
            "weight": 4
        }, 
        {
            "source": "('test/unit/test_mp.py', '(func:1558:(test_start_parent:1620))')", 
            "target": "('src/gofer/mp.py', '(func:1237:(start:1241))')", 
            "weight": 4
        }, 
        {
            "source": "('src/gofer/common.py', '(func:1826:(all:1848))')", 
            "target": "('src/gofer/common.py', '(func:4574:(__getattr__:4578))')", 
            "weight": 4
        }, 
        {
            "source": "('test/unit/test_collator.py', '(func:816:(test_init:820))')", 
            "target": "('src/gofer/collator.py', '__init__:28')", 
            "weight": 4
        }, 
        {
            "source": "('test/unit/test_common.py', '(func:6131:(test_getattr:6135))')", 
            "target": "('src/gofer/common.py', '(func:4125:(__init__:4129))')", 
            "weight": 4
        }, 
        {
            "source": "('test/unit/test_config.py', '(func:7507:(test_setitem:7511))')", 
            "target": "('src/gofer/config.py', '(func:7746:(__setitem__:7750))')", 
            "weight": 4
        }, 
        {
            "source": "('test/unit/test_config.py', '(func:7507:(test_setitem:7511))')", 
            "target": "('src/gofer/config.py', '(func:4761:(__init__:4765))')", 
            "weight": 4
        }, 
        {
            "source": "('test/unit/test_decorators.py', '(func:1477:(test_secret:1519))')", 
            "target": "('src/gofer/decorators.py', '(func:1338:(inner:1342))')", 
            "weight": 4
        }, 
        {
            "source": "('test/unit/test_decorators.py', '(func:1477:(test_secret:1519))')", 
            "target": "('src/gofer/decorators.py', '(func:1099:(remote:1103))')", 
            "weight": 4
        }, 
        {
            "source": "('test/unit/test_config.py', '(func:16130:(test_repr:16134))')", 
            "target": "('src/gofer/config.py', '(func:14466:(__init__:14470))')", 
            "weight": 4
        }, 
        {
            "source": "('test/unit/test_config.py', '(func:9517:(test_get:9574))')", 
            "target": "('src/gofer/config.py', '(func:10119:(get:10141))')", 
            "weight": 4
        }, 
        {
            "source": "('test/unit/test_common.py', '(func:9389:(test_all:9393))')", 
            "target": "('src/gofer/common.py', '(func:2652:(sfn:2656))')", 
            "weight": 4
        }, 
        {
            "source": "('src/gofer/config.py', '(func:15313:(__str__:15317))')", 
            "target": "('src/gofer/config.py', '(func:15640:(__new__:15644))')", 
            "weight": 4
        }, 
        {
            "source": "('src/gofer/config.py', '(func:5493:(open:5497))')", 
            "target": "('src/gofer/config.py', '(func:18118:(read:18122))')", 
            "weight": 4
        }, 
        {
            "source": "('test/unit/test_common.py', '(func:5908:(test_aborted:5954))')", 
            "target": "('src/gofer/common.py', '(func:1981:(__init__:1985))')", 
            "weight": 4
        }, 
        {
            "source": "('test/unit/test_common.py', '(func:5908:(test_aborted:5954))')", 
            "target": "('src/gofer/common.py', '(func:2122:(aborted:2144))')", 
            "weight": 4
        }, 
        {
            "source": "('test/unit/test_metrics.py', '(func:5362:(test_sizeof_not_formatted:5366))')", 
            "target": "('src/gofer/metrics.py', '(func:3590:(sizeof:3612))')", 
            "weight": 4
        }, 
        {
            "source": "('src/gofer/config.py', '(func:11677:(validate:11681))')", 
            "target": "('src/gofer/config.py', '(func:12156:(valid_property:12160))')", 
            "weight": 4
        }, 
        {
            "source": "('src/gofer/config.py', '(func:11677:(validate:11681))')", 
            "target": "('src/gofer/config.py', '(func:3181:(__init__:3185))')", 
            "weight": 4
        }, 
        {
            "source": "('test/unit/test_common.py', '(func:6230:(test_get_item:6234))')", 
            "target": "('src/gofer/common.py', '(func:4125:(__init__:4129))')", 
            "weight": 4
        }, 
        {
            "source": "('test/unit/test_common.py', '(func:6230:(test_get_item:6234))')", 
            "target": "('src/gofer/common.py', '(func:4578:(__getitem__:4582))')", 
            "weight": 4
        }, 
        {
            "source": "('test/unit/test_mp.py', '(func:6109:(test_poll:6143))')", 
            "target": "('src/gofer/mp.py', '(func:4886:(poll:4890))')", 
            "weight": 4
        }, 
        {
            "source": "('test/unit/test_mp.py', '(func:6109:(test_poll:6143))')", 
            "target": "('src/gofer/mp.py', '(func:4142:(__init__:4146))')", 
            "weight": 4
        }, 
        {
            "source": "('test/unit/test_config.py', '(func:7940:(test_validate_real:7944))')", 
            "target": "('src/gofer/config.py', '(func:8483:(validate:8487))')", 
            "weight": 4
        }, 
        {
            "source": "('test/unit/test_config.py', '(func:7940:(test_validate_real:7944))')", 
            "target": "('src/gofer/config.py', '(func:4761:(__init__:4765))')", 
            "weight": 4
        }, 
        {
            "source": "('test/unit/test_config.py', '(func:7940:(test_validate_real:7944))')", 
            "target": "('src/gofer/config.py', '(func:8331:(__init__:8335))')", 
            "weight": 4
        }, 
        {
            "source": "('src/gofer/config.py', '(func:3181:(__init__:3185))')", 
            "target": "('src/gofer/config.py', '(func:2869:(__init__:2873))')", 
            "weight": 4
        }, 
        {
            "source": "('src/gofer/config.py', '(func:19961:(__call__:19965))')", 
            "target": "('src/gofer/config.py', '(func:19315:(split:19337))')", 
            "weight": 4
        }, 
        {
            "source": "('src/gofer/config.py', '(func:19961:(__call__:19965))')", 
            "target": "('src/gofer/config.py', '(func:16578:(read:16582))')", 
            "weight": 4
        }, 
        {
            "source": "('src/gofer/config.py', '(func:19961:(__call__:19965))')", 
            "target": "('src/gofer/config.py', '(func:17528:(read:17532))')", 
            "weight": 4
        }, 
        {
            "source": "('test/unit/test_mp.py', '(func:2161:(test_terminate:2187))')", 
            "target": "('src/gofer/mp.py', '(func:1089:(__init__:1093))')", 
            "weight": 4
        }, 
        {
            "source": "('test/unit/test_mp.py', '(func:5635:(test_multiple_write_read:5639))')", 
            "target": "('src/gofer/mp.py', '(func:2636:(close:2640))')", 
            "weight": 4
        }, 
        {
            "source": "('test/unit/test_mp.py', '(func:5635:(test_multiple_write_read:5639))')", 
            "target": "('src/gofer/mp.py', '(func:4388:(get:4392))')", 
            "weight": 4
        }, 
        {
            "source": "('test/unit/test_mp.py', '(func:5635:(test_multiple_write_read:5639))')", 
            "target": "('src/gofer/mp.py', '(func:3172:(put:3176))')", 
            "weight": 4
        }, 
        {
            "source": "('test/unit/test_mp.py', '(func:5635:(test_multiple_write_read:5639))')", 
            "target": "('src/gofer/mp.py', '(func:2514:(__init__:2518))')", 
            "weight": 4
        }, 
        {
            "source": "('test/unit/test_config.py', '(func:2862:(test_validation_exception:2866))')", 
            "target": "('src/gofer/config.py', '(func:2869:(__init__:2873))')", 
            "weight": 4
        }, 
        {
            "source": "('src/gofer/decorators.py', '(func:1338:(inner:1342))')", 
            "target": "('src/gofer/common.py', '(func:4125:(__init__:4129))')", 
            "weight": 4
        }, 
        {
            "source": "('src/gofer/decorators.py', '(func:1338:(inner:1342))')", 
            "target": "('src/gofer/decorators.py', '(func:773:(options:777))')", 
            "weight": 4
        }, 
        {
            "source": "('test/unit/test_common.py', '(func:7112:(test_iter:7116))')", 
            "target": "('src/gofer/common.py', '(func:4125:(__init__:4129))')", 
            "weight": 4
        }, 
        {
            "source": "('test/unit/test_config.py', '(func:14402:(test_iter:14406))')", 
            "target": "('src/gofer/config.py', '(func:14466:(__init__:14470))')", 
            "weight": 4
        }, 
        {
            "source": "('test/unit/test_common.py', '(func:6604:(test_purge:6608))')", 
            "target": "('src/gofer/common.py', '(func:1826:(all:1848))')", 
            "weight": 4
        }, 
        {
            "source": "('test/unit/test_common.py', '(func:6604:(test_purge:6608))')", 
            "target": "('src/gofer/common.py', '(func:4549:(purge:4571))')", 
            "weight": 4
        }, 
        {
            "source": "('test/unit/test_common.py', '(func:6458:(test_iadd_object:6462))')", 
            "target": "('src/gofer/common.py', '(func:4125:(__init__:4129))')", 
            "weight": 4
        }, 
        {
            "source": "('src/gofer/config.py', '(func:18118:(read:18122))')", 
            "target": "('src/gofer/config.py', '(func:16578:(read:16582))')", 
            "weight": 4
        }, 
        {
            "source": "('src/gofer/config.py', '(func:18118:(read:18122))')", 
            "target": "('src/gofer/config.py', '(func:17528:(read:17532))')", 
            "weight": 4
        }, 
        {
            "source": "('test/unit/test_collator.py', '(func:5249:(test_decorated:5253))')", 
            "target": "('src/gofer/collator.py', '__init__:28')", 
            "weight": 4
        }, 
        {
            "source": "('test/unit/test_collator.py', '(func:5249:(test_decorated:5253))')", 
            "target": "('src/gofer/collator.py', '__decorated:92')", 
            "weight": 4
        }, 
        {
            "source": "('test/unit/test_config.py', '(func:4574:(test_property_not_valid:4578))')", 
            "target": "('src/gofer/config.py', '(func:3713:(__init__:3717))')", 
            "weight": 4
        }, 
        {
            "source": "('test/unit/test_config.py', '(func:11327:(test_validate:11381))')", 
            "target": "('src/gofer/config.py', '(func:11677:(validate:11681))')", 
            "weight": 4
        }, 
        {
            "source": "('test/unit/test_config.py', '(func:5845:(test_open:5919))')", 
            "target": "('src/gofer/config.py', '(func:5493:(open:5497))')", 
            "weight": 4
        }, 
        {
            "source": "('test/unit/test_config.py', '(func:5845:(test_open:5919))')", 
            "target": "('src/gofer/config.py', '(func:4761:(__init__:4765))')", 
            "weight": 4
        }, 
        {
            "source": "('test/unit/test_config.py', '(func:6845:(test_graph:6882))')", 
            "target": "('src/gofer/config.py', '(func:6665:(graph:6669))')", 
            "weight": 4
        }, 
        {
            "source": "('test/unit/test_config.py', '(func:6845:(test_graph:6882))')", 
            "target": "('src/gofer/config.py', '(func:4761:(__init__:4765))')", 
            "weight": 4
        }, 
        {
            "source": "('test/unit/test_collator.py', '(func:1016:(test_collate:1132))')", 
            "target": "('src/gofer/collator.py', 'collate:33')", 
            "weight": 4
        }, 
        {
            "source": "('test/unit/test_collator.py', '(func:1016:(test_collate:1132))')", 
            "target": "('src/gofer/collator.py', '__init__:28')", 
            "weight": 4
        }, 
        {
            "source": "('src/gofer/proxy.py', '(func:708:(__init__:712))')", 
            "target": "('src/gofer/rmi/container.py', '(func:1186:(__init__:1190))')", 
            "weight": 4
        }, 
        {
            "source": "('test/unit/test_config.py', '(func:5469:(test_init:5592))')", 
            "target": "('src/gofer/config.py', '(func:19961:(__call__:19965))')", 
            "weight": 4
        }, 
        {
            "source": "('test/unit/test_config.py', '(func:5469:(test_init:5592))')", 
            "target": "('src/gofer/config.py', '(func:4761:(__init__:4765))')", 
            "weight": 4
        }, 
        {
            "source": "('src/gofer/common.py', '(func:936:(utf8:940))')", 
            "target": "('src/gofer/common.py', '(func:5118:(__repr__:5122))')", 
            "weight": 4
        }, 
        {
            "source": "('src/gofer/common.py', '(func:936:(utf8:940))')", 
            "target": "('src/gofer/config.py', '(func:15313:(__str__:15317))')", 
            "weight": 4
        }, 
        {
            "source": "('src/gofer/config.py', '(func:4761:(__init__:4765))')", 
            "target": "('src/gofer/config.py', '(func:19961:(__call__:19965))')", 
            "weight": 4
        }, 
        {
            "source": "('src/gofer/config.py', '(func:4761:(__init__:4765))')", 
            "target": "('src/gofer/config.py', '(func:6292:(update:6296))')", 
            "weight": 4
        }, 
        {
            "source": "('test/unit/test_config.py', '(func:17786:(test_read:17790))')", 
            "target": "('src/gofer/config.py', '(func:17528:(read:17532))')", 
            "weight": 4
        }, 
        {
            "source": "('test/unit/test_config.py', '(func:12659:(test_validate:12663))')", 
            "target": "('src/gofer/config.py', '(func:13171:(__init__:13175))')", 
            "weight": 4
        }, 
        {
            "source": "('src/gofer/common.py', '(func:2027:(__call__:2031))')", 
            "target": "('src/gofer/common.py', '(func:1826:(all:1848))')", 
            "weight": 4
        }, 
        {
            "source": "('src/gofer/common.py', '(func:2027:(__call__:2031))')", 
            "target": "('test/unit/test_common.py', '(func:1226:(__init__:1230))')", 
            "weight": 4
        }, 
        {
            "source": "('src/gofer/common.py', '(func:2027:(__call__:2031))')", 
            "target": "('test/unit/test_common.py', '(func:1441:(__init__:1445))')", 
            "weight": 4
        }, 
        {
            "source": "('src/gofer/common.py', '(func:2027:(__call__:2031))')", 
            "target": "('src/gofer/common.py', '(func:1026:(key:1048))')", 
            "weight": 4
        }, 
        {
            "source": "('src/gofer/collator.py', '__functions:81')", 
            "target": "('src/gofer/collator.py', '__decorated:92')", 
            "weight": 4
        }, 
        {
            "source": "('src/gofer/metrics.py', '(func:3846:(_sizeof:3868))')", 
            "target": "('src/gofer/metrics.py', '(func:3846:(_sizeof:3868))')", 
            "weight": 4
        }, 
        {
            "source": "('test/unit/test_collator.py', '(func:5750:(test_list:5754))')", 
            "target": "('src/gofer/collator.py', 'collate:33')", 
            "weight": 4
        }, 
        {
            "source": "('test/unit/test_collator.py', '(func:5750:(test_list:5754))')", 
            "target": "('src/gofer/collator.py', '__init__:28')", 
            "weight": 4
        }, 
        {
            "source": "('test/unit/test_metrics.py', '(func:1006:(test_stop:1034))')", 
            "target": "('src/gofer/metrics.py', '(func:778:(__init__:782))')", 
            "weight": 4
        }, 
        {
            "source": "('src/gofer/decorators.py', '(func:1099:(remote:1103))')", 
            "target": "('src/gofer/decorators.py', '(func:1338:(inner:1342))')", 
            "weight": 4
        }, 
        {
            "source": "('test/unit/test_config.py', '(func:3307:(test_section_not_found:3311))')", 
            "target": "('src/gofer/config.py', '(func:3181:(__init__:3185))')", 
            "weight": 4
        }, 
        {
            "source": "('test/unit/test_decorators.py', '(func:3017:(test_call:3021))')", 
            "target": "('src/gofer/decorators.py', '(func:2290:(fork:2294))')", 
            "weight": 4
        }, 
        {
            "source": "('test/unit/test_mp.py', '(func:4164:(test_put:4203))')", 
            "target": "('src/gofer/mp.py', '(func:3172:(put:3176))')", 
            "weight": 4
        }, 
        {
            "source": "('test/unit/test_mp.py', '(func:4164:(test_put:4203))')", 
            "target": "('src/gofer/mp.py', '(func:2514:(__init__:2518))')", 
            "weight": 4
        }, 
        {
            "source": "('test/unit/test_collator.py', '(func:6256:(test_dictionary:6260))')", 
            "target": "('src/gofer/collator.py', 'collate:33')", 
            "weight": 4
        }, 
        {
            "source": "('test/unit/test_collator.py', '(func:6256:(test_dictionary:6260))')", 
            "target": "('src/gofer/collator.py', '__init__:28')", 
            "weight": 4
        }, 
        {
            "source": "('test/unit/test_collator.py', '(func:3430:(test_methods:3467))')", 
            "target": "('src/gofer/collator.py', '__methods:74')", 
            "weight": 4
        }, 
        {
            "source": "('test/unit/test_collator.py', '(func:3430:(test_methods:3467))')", 
            "target": "('src/gofer/collator.py', '__init__:28')", 
            "weight": 4
        }, 
        {
            "source": "('src/gofer/metrics.py', '(func:3590:(sizeof:3612))')", 
            "target": "('src/gofer/metrics.py', '(func:3232:(format:3254))')", 
            "weight": 4
        }, 
        {
            "source": "('src/gofer/metrics.py', '(func:3590:(sizeof:3612))')", 
            "target": "('src/gofer/metrics.py', '(func:3846:(_sizeof:3868))')", 
            "weight": 4
        }, 
        {
            "source": "('test/unit/test_config.py', '(func:14853:(test_repr:14857))')", 
            "target": "('src/gofer/config.py', '(func:14466:(__init__:14470))')", 
            "weight": 4
        }, 
        {
            "source": "('test/unit/test_metrics.py', '(func:5060:(test_sizeof_history:5064))')", 
            "target": "('src/gofer/metrics.py', '(func:3846:(_sizeof:3868))')", 
            "weight": 4
        }, 
        {
            "source": "('test/unit/test_decorators.py', '(func:981:(test_options_already:985))')", 
            "target": "('src/gofer/decorators.py', '(func:773:(options:777))')", 
            "weight": 4
        }, 
        {
            "source": "('test/unit/test_common.py', '(func:5324:(test_condition:5328))')", 
            "target": "('src/gofer/common.py', '(func:3475:(sfn:3479))')", 
            "weight": 4
        }, 
        {
            "source": "('src/gofer/mp.py', '(func:4142:(__init__:4146))')", 
            "target": "('src/gofer/mp.py', '(func:3638:(__init__:3642))')", 
            "weight": 4
        }, 
        {
            "source": "('test/unit/test_collator.py', '(func:3019:(test_classes:3053))')", 
            "target": "('src/gofer/collator.py', '__init__:28')", 
            "weight": 4
        }, 
        {
            "source": "('test/unit/test_config.py', '(func:18581:(test_iread:18616))')", 
            "target": "('src/gofer/config.py', '(func:18118:(read:18122))')", 
            "weight": 4
        }, 
        {
            "source": "('src/gofer/mp.py', '(func:3172:(put:3176))')", 
            "target": "('src/gofer/mp.py', '(func:5077:(put:5081))')", 
            "weight": 4
        }, 
        {
            "source": "('test/unit/test_config.py', '(func:19295:(test_jread:19330))')", 
            "target": "('src/gofer/config.py', '(func:18118:(read:18122))')", 
            "weight": 4
        }, 
        {
            "source": "('src/gofer/config.py', '(func:3476:(__init__:3480))')", 
            "target": "('src/gofer/config.py', '(func:2869:(__init__:2873))')", 
            "weight": 4
        }, 
        {
            "source": "('test/unit/test_common.py', '(func:2005:(test_call:2009))')", 
            "target": "('src/gofer/common.py', '(func:1410:(__call__:1414))')", 
            "weight": 4
        }, 
        {
            "source": "('test/unit/test_metrics.py', '(func:2958:(test_context:2962))')", 
            "target": "('src/gofer/metrics.py', '(func:778:(__init__:782))')", 
            "weight": 4
        }, 
        {
            "source": "('src/gofer/collator.py', '__map:56')", 
            "target": "('src/gofer/collator.py', '__methods:74')", 
            "weight": 4
        }, 
        {
            "source": "('src/gofer/collator.py', '__map:56')", 
            "target": "('src/gofer/collator.py', '__decorated:92')", 
            "weight": 4
        }, 
        {
            "source": "('src/gofer/collator.py', '__map:56')", 
            "target": "('src/gofer/collator.py', '__function:77')", 
            "weight": 4
        }, 
        {
            "source": "('src/gofer/decorators.py', '(func:773:(options:777))')", 
            "target": "('src/gofer/common.py', '(func:4125:(__init__:4129))')", 
            "weight": 4
        }, 
        {
            "source": "('test/unit/test_config.py', '(func:15534:(test_strict_get:15538))')", 
            "target": "('src/gofer/config.py', '(func:14466:(__init__:14470))')", 
            "weight": 4
        }, 
        {
            "source": "('test/unit/test_config.py', '(func:13244:(test_accessing:13248))')", 
            "target": "('src/gofer/config.py', '(func:14466:(__init__:14470))')", 
            "weight": 4
        }, 
        {
            "source": "('test/unit/test_common.py', '(func:5751:(test_init:5755))')", 
            "target": "('src/gofer/common.py', '(func:1981:(__init__:1985))')", 
            "weight": 4
        }, 
        {
            "source": "('src/gofer/decorators.py', '(func:2290:(fork:2294))')", 
            "target": "('src/gofer/decorators.py', '(func:773:(options:777))')", 
            "weight": 4
        }, 
        {
            "source": "('src/gofer/common.py', '(func:4549:(purge:4571))')", 
            "target": "('src/gofer/common.py', '(func:4478:(__setattr__:4482))')", 
            "weight": 4
        }, 
        {
            "source": "('src/gofer/common.py', '(func:4549:(purge:4571))')", 
            "target": "('src/gofer/common.py', '(func:1826:(all:1848))')", 
            "weight": 4
        }, 
        {
            "source": "('src/gofer/config.py', '(func:3713:(__init__:3717))')", 
            "target": "('src/gofer/config.py', '(func:2869:(__init__:2873))')", 
            "weight": 4
        }, 
        {
            "source": "('src/gofer/common.py', '(func:1410:(__call__:1414))')", 
            "target": "('test/unit/test_common.py', '(func:834:(__init__:838))')", 
            "weight": 4
        }, 
        {
            "source": "('src/gofer/common.py', '(func:1410:(__call__:1414))')", 
            "target": "('src/gofer/common.py', '(func:1026:(key:1048))')", 
            "weight": 4
        }, 
        {
            "source": "('src/gofer/common.py', '(func:1410:(__call__:1414))')", 
            "target": "('test/unit/test_common.py', '(func:1042:(__init__:1046))')", 
            "weight": 4
        }, 
        {
            "source": "('src/gofer/config.py', '(func:8483:(validate:8487))')", 
            "target": "('src/gofer/config.py', '(func:8974:(undefined:8978))')", 
            "weight": 4
        }, 
        {
            "source": "('src/gofer/config.py', '(func:8483:(validate:8487))')", 
            "target": "('src/gofer/config.py', '(func:11677:(validate:11681))')", 
            "weight": 4
        }, 
        {
            "source": "('test/unit/test_mp.py', '(func:3878:(test_get:3917))')", 
            "target": "('src/gofer/mp.py', '(func:2514:(__init__:2518))')", 
            "weight": 4
        }, 
        {
            "source": "('test/unit/test_mp.py', '(func:3878:(test_get:3917))')", 
            "target": "('src/gofer/mp.py', '(func:2980:(get:2984))')", 
            "weight": 4
        }, 
        {
            "source": "('test/unit/test_common.py', '(func:4320:(test_call_different_thread:4324))')", 
            "target": "('src/gofer/common.py', '(func:1826:(all:1848))')", 
            "weight": 4
        }, 
        {
            "source": "('test/unit/test_common.py', '(func:4320:(test_call_different_thread:4324))')", 
            "target": "('src/gofer/common.py', '(func:2027:(__call__:2031))')", 
            "weight": 4
        }, 
        {
            "source": "('test/unit/test_common.py', '(func:3432:(test_call:3436))')", 
            "target": "('src/gofer/common.py', '(func:1826:(all:1848))')", 
            "weight": 4
        }, 
        {
            "source": "('test/unit/test_common.py', '(func:3432:(test_call:3436))')", 
            "target": "('src/gofer/common.py', '(func:2027:(__call__:2031))')", 
            "weight": 4
        }, 
        {
            "source": "('src/gofer/config.py', '(func:10119:(get:10141))')", 
            "target": "('src/gofer/config.py', '(func:10958:(__unlock:10980))')", 
            "weight": 4
        }, 
        {
            "source": "('src/gofer/config.py', '(func:10119:(get:10141))')", 
            "target": "('src/gofer/config.py', '(func:10886:(__lock:10908))')", 
            "weight": 4
        }, 
        {
            "source": "('test/unit/test_common.py', '(func:6494:(test_all:6498))')", 
            "target": "('src/gofer/common.py', '(func:1826:(all:1848))')", 
            "weight": 4
        }, 
        {
            "source": "('test/unit/test_config.py', '(func:11847:(test_valid_property:11896))')", 
            "target": "('src/gofer/config.py', '(func:12156:(valid_property:12160))')", 
            "weight": 4
        }, 
        {
            "source": "('test/unit/test_config.py', '(func:11847:(test_valid_property:11896))')", 
            "target": "('src/gofer/config.py', '(func:3476:(__init__:3480))')", 
            "weight": 4
        }, 
        {
            "source": "('test/unit/test_mp.py', '(func:2496:(test_wait:2525))')", 
            "target": "('src/gofer/mp.py', '(func:1089:(__init__:1093))')", 
            "weight": 4
        }, 
        {
            "source": "('test/unit/test_mp.py', '(func:2496:(test_wait:2525))')", 
            "target": "('src/gofer/mp.py', '(func:1825:(wait:1829))')", 
            "weight": 4
        }, 
        {
            "source": "('test/unit/test_mp.py', '(func:4961:(test_close:4988))')", 
            "target": "('src/gofer/mp.py', '(func:3638:(__init__:3642))')", 
            "weight": 4
        }, 
        {
            "source": "('src/gofer/collator.py', 'collate:33')", 
            "target": "('src/gofer/collator.py', '__map:56')", 
            "weight": 4
        }, 
        {
            "source": "('src/gofer/collator.py', 'collate:33')", 
            "target": "('src/gofer/collator.py', '__functions:81')", 
            "weight": 4
        }, 
        {
            "source": "('test/unit/test_mp.py', '(func:3068:(test_init:3107))')", 
            "target": "('src/gofer/mp.py', '(func:4142:(__init__:4146))')", 
            "weight": 4
        }, 
        {
            "source": "('test/unit/test_mp.py', '(func:3068:(test_init:3107))')", 
            "target": "('src/gofer/mp.py', '(func:3638:(__init__:3642))')", 
            "weight": 4
        }, 
        {
            "source": "('test/unit/test_mp.py', '(func:3068:(test_init:3107))')", 
            "target": "('src/gofer/mp.py', '(func:2514:(__init__:2518))')", 
            "weight": 4
        }, 
        {
            "source": "('test/unit/test_common.py', '(func:10044:(test_unicode:10048))')", 
            "target": "('src/gofer/common.py', '(func:4125:(__init__:4129))')", 
            "weight": 4
        }, 
        {
            "source": "('test/unit/test_common.py', '(func:10044:(test_unicode:10048))')", 
            "target": "('src/gofer/common.py', '(func:8176:(__unicode__:8180))')", 
            "weight": 4
        }, 
        {
            "source": "('test/unit/test_mp.py', '(func:3669:(test_poll:3708))')", 
            "target": "('src/gofer/mp.py', '(func:2514:(__init__:2518))')", 
            "weight": 4
        }, 
        {
            "source": "('test/unit/test_mp.py', '(func:3669:(test_poll:3708))')", 
            "target": "('src/gofer/mp.py', '(func:2787:(poll:2791))')", 
            "weight": 4
        }, 
        {
            "source": "('src/gofer/rmi/container.py', '(func:1186:(__init__:1190))')", 
            "target": "('src/gofer/common.py', '(func:4125:(__init__:4129))')", 
            "weight": 4
        }, 
        {
            "source": "('test/unit/test_mp.py', '(func:4404:(test_enter:4443))')", 
            "target": "('src/gofer/mp.py', '(func:2514:(__init__:2518))')", 
            "weight": 4
        }, 
        {
            "source": "('test/unit/test_decorators.py', '(func:1830:(test_call:1834))')", 
            "target": "('src/gofer/decorators.py', '(func:1676:(pam:1680))')", 
            "weight": 4
        }, 
        {
            "source": "('test/unit/test_common.py', '(func:4899:(test_synchronized:4903))')", 
            "target": "('src/gofer/common.py', '(func:2652:(sfn:2656))')", 
            "weight": 4
        }, 
        {
            "source": "('test/unit/test_common.py', '(func:7254:(test_repr:7258))')", 
            "target": "('src/gofer/common.py', '(func:4125:(__init__:4129))')", 
            "weight": 4
        }, 
        {
            "source": "('test/unit/test_config.py', '(func:16282:(test_iter:16286))')", 
            "target": "('src/gofer/config.py', '(func:14466:(__init__:14470))')", 
            "weight": 4
        }, 
        {
            "source": "('test/unit/test_mp.py', '(func:1905:(test_run:1909))')", 
            "target": "('src/gofer/mp.py', '(func:1089:(__init__:1093))')", 
            "weight": 4
        }, 
        {
            "source": "('test/unit/test_mp.py', '(func:1265:(test_start_child:1327))')", 
            "target": "('src/gofer/mp.py', '(func:1089:(__init__:1093))')", 
            "weight": 4
        }, 
        {
            "source": "('test/unit/test_mp.py', '(func:1265:(test_start_child:1327))')", 
            "target": "('src/gofer/mp.py', '(func:1237:(start:1241))')", 
            "weight": 4
        }
    ], 
    "nodes": [
        {
            "AST Diff": 0, 
            "Profile Diff": false, 
            "id": "('test/unit/test_common.py', '(func:9389:(test_all:9393))')", 
            "md5": "a7aba5b5fbf1ef85200662caa74e6d07", 
            "weight": 2
        }, 
        {
            "AST Diff": 0, 
            "Profile Diff": false, 
            "id": "('src/gofer/config.py', '(func:18923:(match:18945))')", 
            "md5": "b4de6f801c2fe9f5b959efa339509c74", 
            "weight": 2
        }, 
        {
            "AST Diff": 0, 
            "Profile Diff": false, 
            "id": "('src/gofer/collator.py', '__map:56')", 
            "md5": "b67e54b4c2823ec1b0296acc427c4de2", 
            "weight": 2
        }, 
        {
            "AST Diff": 0, 
            "Profile Diff": false, 
            "id": "('src/gofer/config.py', '(func:5493:(open:5497))')", 
            "md5": "72bb92c5673590af3cd091a008f21d49", 
            "weight": 2
        }, 
        {
            "AST Diff": 0, 
            "Profile Diff": false, 
            "id": "('test/unit/test_collator.py', '(func:4145:(test_functions:4240))')", 
            "md5": "d428d1913e45eca9292156554bd3b2e3", 
            "weight": 2
        }, 
        {
            "AST Diff": 0, 
            "Profile Diff": false, 
            "id": "('src/gofer/mp.py', '(func:2980:(get:2984))')", 
            "md5": "4b42decc7b73c9cb4fa85c0a2f5dba6d", 
            "weight": 2
        }, 
        {
            "AST Diff": 0, 
            "Profile Diff": false, 
            "id": "('test/unit/test_config.py', '(func:12412:(test_init:12416))')", 
            "md5": "7758b5933a463f6a2a39343809cc47a3", 
            "weight": 2
        }, 
        {
            "AST Diff": 0, 
            "Profile Diff": false, 
            "id": "('test/unit/test_collator.py', '(func:1649:(test_map:1884))')", 
            "md5": "515cdce0a75b256b2d50747ee80662cc", 
            "weight": 2
        }, 
        {
            "AST Diff": 0, 
            "Profile Diff": false, 
            "id": "('test/unit/test_metrics.py', '(func:1006:(test_stop:1034))')", 
            "md5": "c597f6694b3d7bee0827172b2d3574e5", 
            "weight": 2
        }, 
        {
            "AST Diff": 0, 
            "Profile Diff": false, 
            "id": "('test/unit/test_collator.py', '(func:3430:(test_methods:3467))')", 
            "md5": "1a6f6da9d790091aa4d18ab9b3f520ce", 
            "weight": 2
        }, 
        {
            "AST Diff": 0, 
            "Profile Diff": false, 
            "id": "('src/gofer/common.py', '(func:2027:(__call__:2031))')", 
            "md5": "3ad3217881d8a2a0cda7a0759c9b6155", 
            "weight": 2
        }, 
        {
            "AST Diff": 0, 
            "Profile Diff": false, 
            "id": "('src/gofer/config.py', '(func:15313:(__str__:15317))')", 
            "md5": "b80c08480619943387cc78a4abc47e74", 
            "weight": 2
        }, 
        {
            "AST Diff": 0, 
            "Profile Diff": false, 
            "id": "('src/gofer/decorators.py', '(func:773:(options:777))')", 
            "md5": "15cabc009279f4f9c3d7b5e728a50c9c", 
            "weight": 2
        }, 
        {
            "AST Diff": 0, 
            "Profile Diff": false, 
            "id": "('test/unit/test_common.py', '(func:1441:(__init__:1445))')", 
            "md5": "4b67a5a7d51183a0a66dbf38036370f9", 
            "weight": 2
        }, 
        {
            "AST Diff": 0, 
            "Profile Diff": false, 
            "id": "('test/unit/test_decorators.py', '(func:1224:(test_call:1266))')", 
            "md5": "8e0b00abaa2d7fef7eb19cd969779016", 
            "weight": 2
        }, 
        {
            "AST Diff": 0, 
            "Profile Diff": false, 
            "id": "('src/gofer/collator.py', '__functions:81')", 
            "md5": "23a1f3339d3f30f9b476f726089ebb34", 
            "weight": 2
        }, 
        {
            "AST Diff": 0, 
            "Profile Diff": false, 
            "id": "('test/unit/test_mp.py', '(func:4845:(test_init:4849))')", 
            "md5": "fe7c7b14d8140161036d0aefc786577a", 
            "weight": 2
        }, 
        {
            "AST Diff": 0, 
            "Profile Diff": false, 
            "id": "('test/unit/test_config.py', '(func:13244:(test_accessing:13248))')", 
            "md5": "db26483248bf7f3a987b8214a5f9e178", 
            "weight": 2
        }, 
        {
            "AST Diff": 0, 
            "Profile Diff": false, 
            "id": "('test/unit/test_mp.py', '(func:4579:(test_exit:4653))')", 
            "md5": "1369e353f2b68a318bf0018f9e527590", 
            "weight": 2
        }, 
        {
            "AST Diff": 0, 
            "Profile Diff": false, 
            "id": "('src/gofer/metrics.py', '(func:3846:(_sizeof:3868))')", 
            "md5": "027a0cc2aa120fe75ece44d2c089142c", 
            "weight": 2
        }, 
        {
            "AST Diff": 0, 
            "Profile Diff": false, 
            "id": "('test/unit/test_common.py', '(func:5751:(test_init:5755))')", 
            "md5": "cf838773f78c74a41a6d560939252760", 
            "weight": 2
        }, 
        {
            "AST Diff": 0, 
            "Profile Diff": false, 
            "id": "('src/gofer/common.py', '(func:5887:(_fn:5891))')", 
            "md5": "dee57195ce6ff1ba248bcaf32569bbb8", 
            "weight": 2
        }, 
        {
            "AST Diff": 0, 
            "Profile Diff": false, 
            "id": "('src/gofer/decorators.py', '(func:2290:(fork:2294))')", 
            "md5": "a4beee1c07e048337e985c05da00956a", 
            "weight": 2
        }, 
        {
            "AST Diff": 0, 
            "Profile Diff": false, 
            "id": "('test/unit/test_collator.py', '(func:5249:(test_decorated:5253))')", 
            "md5": "7a4eec0a8165e8e029d9b2e0d47d70dc", 
            "weight": 2
        }, 
        {
            "AST Diff": 0, 
            "Profile Diff": false, 
            "id": "('src/gofer/common.py', '(func:4549:(purge:4571))')", 
            "md5": "03766312301c730c727f86e45eeddcb6", 
            "weight": 2
        }, 
        {
            "AST Diff": 0, 
            "Profile Diff": false, 
            "id": "('src/gofer/config.py', '(func:14466:(__init__:14470))')", 
            "md5": "a441b604a0d2e81edb125a916ac3839b", 
            "weight": 2
        }, 
        {
            "AST Diff": 0, 
            "Profile Diff": false, 
            "id": "('src/gofer/mp.py', '(func:1089:(__init__:1093))')", 
            "md5": "29143b90cb1465b9a4f14c5dcb563aca", 
            "weight": 2
        }, 
        {
            "AST Diff": 0, 
            "Profile Diff": false, 
            "id": "('src/gofer/common.py', '(func:1410:(__call__:1414))')", 
            "md5": "4627ebb9767ffd6658b421f9e7248d02", 
            "weight": 2
        }, 
        {
            "AST Diff": 0, 
            "Profile Diff": false, 
            "id": "('test/unit/test_mp.py', '(func:947:(test_init:951))')", 
            "md5": "f7c86f1c85068065903ced11ff67738d", 
            "weight": 2
        }, 
        {
            "AST Diff": 0, 
            "Profile Diff": false, 
            "id": "('src/gofer/config.py', '(func:8483:(validate:8487))')", 
            "md5": "9f07b6050a2d9582a8c86b2f0eb412e8", 
            "weight": 2
        }, 
        {
            "AST Diff": 0, 
            "Profile Diff": false, 
            "id": "('src/gofer/config.py', '(func:11677:(validate:11681))')", 
            "md5": "f79464dad6ebece5759f51de4215f9a2", 
            "weight": 2
        }, 
        {
            "AST Diff": 0, 
            "Profile Diff": false, 
            "id": "('test/unit/test_collator.py', '(func:5750:(test_list:5754))')", 
            "md5": "5e05dfaba6fe5244367cf0036e433737", 
            "weight": 2
        }, 
        {
            "AST Diff": 0, 
            "Profile Diff": false, 
            "id": "('test/unit/test_mp.py', '(func:3395:(test_close:3434))')", 
            "md5": "70b0176a7776dc7f61429ef19bcaf809", 
            "weight": 2
        }, 
        {
            "AST Diff": 0, 
            "Profile Diff": false, 
            "id": "('test/unit/test_common.py', '(func:5324:(test_condition:5328))')", 
            "md5": "287eb5aa321cd300f87c5b59f067225a", 
            "weight": 2
        }, 
        {
            "AST Diff": 0, 
            "Profile Diff": false, 
            "id": "('test/unit/test_mp.py', '(func:3878:(test_get:3917))')", 
            "md5": "574cd5c7c7b7018b4730698875dfd51f", 
            "weight": 2
        }, 
        {
            "AST Diff": 0, 
            "Profile Diff": false, 
            "id": "('src/gofer/common.py', '(func:1026:(key:1048))')", 
            "md5": "44a1a8af2b6f4cf4bd4c42b9111fa6e5", 
            "weight": 2
        }, 
        {
            "AST Diff": 0, 
            "Profile Diff": false, 
            "id": "('test/unit/test_common.py', '(func:6230:(test_get_item:6234))')", 
            "md5": "28e6648600f1f652c79f7e7838fca529", 
            "weight": 2
        }, 
        {
            "AST Diff": 0, 
            "Profile Diff": false, 
            "id": "('test/unit/test_config.py', '(func:7052:(test_strict_graph:7089))')", 
            "md5": "1a2e2d4216760b4fc5c6135ab2d0e9cf", 
            "weight": 2
        }, 
        {
            "AST Diff": 0, 
            "Profile Diff": false, 
            "id": "('test/unit/test_common.py', '(func:1042:(__init__:1046))')", 
            "md5": "add23b690122681184b1e56b1f79698c", 
            "weight": 2
        }, 
        {
            "AST Diff": 0, 
            "Profile Diff": false, 
            "id": "('src/gofer/mp.py', '(func:4886:(poll:4890))')", 
            "md5": "810b56becc9fd8514a6a28a4a156484a", 
            "weight": 2
        }, 
        {
            "AST Diff": 0, 
            "Profile Diff": false, 
            "id": "('src/gofer/config.py', '(func:10119:(get:10141))')", 
            "md5": "19ab2bb501a46d98dd64064aeeac615d", 
            "weight": 2
        }, 
        {
            "AST Diff": 0, 
            "Profile Diff": false, 
            "id": "('src/gofer/decorators.py', '(func:1099:(remote:1103))')", 
            "md5": "205dae030f9fb9e9a80b66a483f5f812", 
            "weight": 2
        }, 
        {
            "AST Diff": 0, 
            "Profile Diff": false, 
            "id": "('src/gofer/rmi/context.py', '(class:Context:765)')", 
            "md5": "14840c75e209d82b92f0ea05320a825c", 
            "weight": 2
        }, 
        {
            "AST Diff": 0, 
            "Profile Diff": false, 
            "id": "('test/unit/test_common.py', '(func:6494:(test_all:6498))')", 
            "md5": "fbafc78853b92129771aeac9d46addca", 
            "weight": 2
        }, 
        {
            "AST Diff": 0, 
            "Profile Diff": false, 
            "id": "('test/unit/test_config.py', '(func:3307:(test_section_not_found:3311))')", 
            "md5": "f3a50f807c23e7febe761375571d9943", 
            "weight": 2
        }, 
        {
            "AST Diff": 0, 
            "Profile Diff": false, 
            "id": "('test/unit/test_decorators.py', '(func:3017:(test_call:3021))')", 
            "md5": "d8387456f6d4f89cab253fc97d39f4ae", 
            "weight": 2
        }, 
        {
            "AST Diff": 0, 
            "Profile Diff": false, 
            "id": "('test/unit/test_mp.py', '(func:2496:(test_wait:2525))')", 
            "md5": "6f95067bb2cd5f64a0cc95f6567ba6c0", 
            "weight": 2
        }, 
        {
            "AST Diff": 0, 
            "Profile Diff": false, 
            "id": "('test/unit/test_decorators.py', '(func:1830:(test_call:1834))')", 
            "md5": "3070ce9e54538828ad91adbaaebe0211", 
            "weight": 2
        }, 
        {
            "AST Diff": 0, 
            "Profile Diff": false, 
            "id": "('test/unit/test_mp.py', '(func:4164:(test_put:4203))')", 
            "md5": "181be5fd9679f97f3a1a7ab6356e3dc9", 
            "weight": 2
        }, 
        {
            "AST Diff": 0, 
            "Profile Diff": false, 
            "id": "('src/gofer/proxy.py', '(func:708:(__init__:712))')", 
            "md5": "b5fd69d475f809f0a7a95a422d7df440", 
            "weight": 2
        }, 
        {
            "AST Diff": 0, 
            "Profile Diff": false, 
            "id": "('src/gofer/collator.py', '__init__:28')", 
            "md5": "896d0dd8ea53ac088ac4feec04c78f00", 
            "weight": 2
        }, 
        {
            "AST Diff": 0, 
            "Profile Diff": false, 
            "id": "('src/gofer/mp.py', '(func:1825:(wait:1829))')", 
            "md5": "4005ee783521e155d0aa5568b854c592", 
            "weight": 2
        }, 
        {
            "AST Diff": 0, 
            "Profile Diff": false, 
            "id": "('test/unit/test_mp.py', '(func:6109:(test_poll:6143))')", 
            "md5": "ef4238061cbc9b8a5fe11385ba2e46ed", 
            "weight": 2
        }, 
        {
            "AST Diff": 0, 
            "Profile Diff": false, 
            "id": "('src/gofer/collator.py', '__function:77')", 
            "md5": "685d5b20ae6895b7e1e7f0dfc92d017e", 
            "weight": 2
        }, 
        {
            "AST Diff": 0, 
            "Profile Diff": false, 
            "id": "('src/gofer/mp.py', '(func:4388:(get:4392))')", 
            "md5": "7f4a91f686a70e97499428aa2b04d4e0", 
            "weight": 2
        }, 
        {
            "AST Diff": 0, 
            "Profile Diff": false, 
            "id": "('test/unit/test_mp.py', '(func:3068:(test_init:3107))')", 
            "md5": "a242f9072fd9379656f1ddbc15cef76b", 
            "weight": 2
        }, 
        {
            "AST Diff": 0, 
            "Profile Diff": false, 
            "id": "('test/unit/test_collator.py', '(func:6256:(test_dictionary:6260))')", 
            "md5": "66e7844eb06b85c98297c7077cab4832", 
            "weight": 2
        }, 
        {
            "AST Diff": 0, 
            "Profile Diff": false, 
            "id": "('src/gofer/decorators.py', '(func:1676:(pam:1680))')", 
            "md5": "da8c340467f795f65fb0ca41750b6b69", 
            "weight": 2
        }, 
        {
            "AST Diff": 0, 
            "Profile Diff": false, 
            "id": "('src/gofer/config.py', '(func:10958:(__unlock:10980))')", 
            "md5": "79c449fc9adedfa42d3fb3d4184e8b29", 
            "weight": 2
        }, 
        {
            "AST Diff": 0, 
            "Profile Diff": false, 
            "id": "('test/unit/test_common.py', '(func:6131:(test_getattr:6135))')", 
            "md5": "2eafa7b4aa0414eef045b45220cb9091", 
            "weight": 2
        }, 
        {
            "AST Diff": 0, 
            "Profile Diff": false, 
            "id": "('test/unit/test_config.py', '(func:7940:(test_validate_real:7944))')", 
            "md5": "d21d6fa3ba5796ec04ae5f0987c6aa26", 
            "weight": 2
        }, 
        {
            "AST Diff": 0, 
            "Profile Diff": false, 
            "id": "('test/unit/test_config.py', '(func:12659:(test_validate:12663))')", 
            "md5": "a4a48aa394d6fbf3543e03630d051f40", 
            "weight": 2
        }, 
        {
            "AST Diff": 0, 
            "Profile Diff": false, 
            "id": "('test/unit/test_mp.py', '(func:3669:(test_poll:3708))')", 
            "md5": "ad1a7840d017170cae3ae239f2fe0fdd", 
            "weight": 2
        }, 
        {
            "AST Diff": 0, 
            "Profile Diff": false, 
            "id": "('src/gofer/config.py', '(func:15196:(__str__:15200))')", 
            "md5": "122f269a0a4e676c0f99eec351b2af23", 
            "weight": 2
        }, 
        {
            "AST Diff": 0, 
            "Profile Diff": false, 
            "id": "('src/gofer/common.py', '(func:1981:(__init__:1985))')", 
            "md5": "6f745d0ea80b3b3c2806a0039ea85aa1", 
            "weight": 2
        }, 
        {
            "AST Diff": 0, 
            "Profile Diff": false, 
            "id": "('test/unit/test_common.py', '(func:5908:(test_aborted:5954))')", 
            "md5": "5dd0d88712d85b793a0b16071e955aac", 
            "weight": 2
        }, 
        {
            "AST Diff": 0, 
            "Profile Diff": false, 
            "id": "('test/unit/test_proxy.py', '(func:671:(test_agent_1:711))')", 
            "md5": "03d9b28c7910d518c90086149a4a3105", 
            "weight": 2
        }, 
        {
            "AST Diff": 0, 
            "Profile Diff": false, 
            "id": "('src/gofer/config.py', '(func:3181:(__init__:3185))')", 
            "md5": "918c06bea643e24c419e221b2cb9b1cd", 
            "weight": 2
        }, 
        {
            "AST Diff": 0, 
            "Profile Diff": false, 
            "id": "('test/unit/test_config.py', '(func:5845:(test_open:5919))')", 
            "md5": "3fab3f3ca92c705b07a670398047667a", 
            "weight": 2
        }, 
        {
            "AST Diff": 0, 
            "Profile Diff": false, 
            "id": "('test/unit/test_mp.py', '(func:5453:(test_write_read:5457))')", 
            "md5": "57eb3186f4e9831799c2f10e9c05ed5b", 
            "weight": 2
        }, 
        {
            "AST Diff": 0, 
            "Profile Diff": false, 
            "id": "('src/gofer/collator.py', '__methods:74')", 
            "md5": "586100dbfde932527cd03563baff99e1", 
            "weight": 2
        }, 
        {
            "AST Diff": 0, 
            "Profile Diff": false, 
            "id": "('src/gofer/config.py', '(func:6665:(graph:6669))')", 
            "md5": "0ee85166efd6c6d9e71bf18f678413cf", 
            "weight": 2
        }, 
        {
            "AST Diff": 0, 
            "Profile Diff": false, 
            "id": "('src/gofer/config.py', '(func:19961:(__call__:19965))')", 
            "md5": "909db9d2f217ccaafd29a068ea02026c", 
            "weight": 2
        }, 
        {
            "AST Diff": 0, 
            "Profile Diff": false, 
            "id": "('src/gofer/metrics.py', '(func:778:(__init__:782))')", 
            "md5": "3c35274de661a23720dc531280542a23", 
            "weight": 2
        }, 
        {
            "AST Diff": 0, 
            "Profile Diff": false, 
            "id": "('src/gofer/metrics.py', '(func:3590:(sizeof:3612))')", 
            "md5": "dbd15f499ea922ede5e2cce8aaf017e3", 
            "weight": 2
        }, 
        {
            "AST Diff": 0, 
            "Profile Diff": false, 
            "id": "('test/unit/test_mp.py', '(func:2161:(test_terminate:2187))')", 
            "md5": "619b6cbe53600eb72ad6f30bdcd62ff6", 
            "weight": 2
        }, 
        {
            "AST Diff": 0, 
            "Profile Diff": false, 
            "id": "('src/gofer/rmi/container.py', '(func:1186:(__init__:1190))')", 
            "md5": "fbedc538f82c0bb5423213492d164a68", 
            "weight": 2
        }, 
        {
            "AST Diff": 0, 
            "Profile Diff": false, 
            "id": "('test/unit/test_mp.py', '(func:5635:(test_multiple_write_read:5639))')", 
            "md5": "260ed05e0892b5f62792c0a4e85f36b0", 
            "weight": 2
        }, 
        {
            "AST Diff": 0, 
            "Profile Diff": false, 
            "id": "('src/gofer/common.py', '(func:2652:(sfn:2656))')", 
            "md5": "48c18a0bb1862708b68bc4fca1a5fe14", 
            "weight": 2
        }, 
        {
            "AST Diff": 0, 
            "Profile Diff": false, 
            "id": "('src/gofer/config.py', '(func:13171:(__init__:13175))')", 
            "md5": "3c565606d5fbfeadaef5a5e35a1c5a7b", 
            "weight": 2
        }, 
        {
            "AST Diff": 0, 
            "Profile Diff": false, 
            "id": "('test/unit/test_config.py', '(func:2862:(test_validation_exception:2866))')", 
            "md5": "d658e2570311407d159d64905eeca3a2", 
            "weight": 2
        }, 
        {
            "AST Diff": 0, 
            "Profile Diff": false, 
            "id": "('src/gofer/decorators.py', '(func:1338:(inner:1342))')", 
            "md5": "4805c731d567a7e6288941d036fb9f0c", 
            "weight": 2
        }, 
        {
            "AST Diff": 0, 
            "Profile Diff": false, 
            "id": "('test/unit/test_mp.py', '(func:1905:(test_run:1909))')", 
            "md5": "468f0ca72cf285cd1b831acdfe71c1ec", 
            "weight": 2
        }, 
        {
            "AST Diff": 0, 
            "Profile Diff": false, 
            "id": "('test/unit/test_config.py', '(func:9517:(test_get:9574))')", 
            "md5": "aeb9a5ebef059164a635b75bb61705f0", 
            "weight": 2
        }, 
        {
            "AST Diff": 0, 
            "Profile Diff": false, 
            "id": "('test/unit/test_metrics.py', '(func:5060:(test_sizeof_history:5064))')", 
            "md5": "32b95f3b82f2eda2445cd31788fb9838", 
            "weight": 2
        }, 
        {
            "AST Diff": 0, 
            "Profile Diff": false, 
            "id": "('test/unit/test_common.py', '(func:7112:(test_iter:7116))')", 
            "md5": "4c8a2d470deca71ecd3245878516c50b", 
            "weight": 2
        }, 
        {
            "AST Diff": 0, 
            "Profile Diff": false, 
            "id": "('test/unit/test_decorators.py', '(func:981:(test_options_already:985))')", 
            "md5": "c9c2b8353b6c583236eaa91e143ebf7c", 
            "weight": 2
        }, 
        {
            "AST Diff": 0, 
            "Profile Diff": false, 
            "id": "('test/unit/test_common.py', '(func:6458:(test_iadd_object:6462))')", 
            "md5": "68d2f771111080b1f714dd3f8c40aa2c", 
            "weight": 2
        }, 
        {
            "AST Diff": 0, 
            "Profile Diff": false, 
            "id": "('test/unit/test_common.py', '(func:3432:(test_call:3436))')", 
            "md5": "85007b13dbe9f68e131187f0daeac9ad", 
            "weight": 2
        }, 
        {
            "AST Diff": 0, 
            "Profile Diff": false, 
            "id": "('src/gofer/config.py', '(func:12156:(valid_property:12160))')", 
            "md5": "da14bf59b79dc20cb49c73709637d99a", 
            "weight": 2
        }, 
        {
            "AST Diff": 0, 
            "Profile Diff": false, 
            "id": "('src/gofer/config.py', '(func:17528:(read:17532))')", 
            "md5": "52840e99d5c066ec939dc6e2da618489", 
            "weight": 2
        }, 
        {
            "AST Diff": 0, 
            "Profile Diff": false, 
            "id": "('test/unit/test_config.py', '(func:14402:(test_iter:14406))')", 
            "md5": "eb8460c3dd2963626b0639d6fe4dcb2a", 
            "weight": 2
        }, 
        {
            "AST Diff": 0, 
            "Profile Diff": false, 
            "id": "('test/unit/test_common.py', '(func:6604:(test_purge:6608))')", 
            "md5": "2b30d261349c25980fc675dd42f08321", 
            "weight": 2
        }, 
        {
            "AST Diff": 0, 
            "Profile Diff": false, 
            "id": "('src/gofer/collator.py', '__decorated:92')", 
            "md5": "e9b49725533dee1e9b590c1543e19380", 
            "weight": 2
        }, 
        {
            "AST Diff": 0, 
            "Profile Diff": false, 
            "id": "('src/gofer/mp.py', '(func:2636:(close:2640))')", 
            "md5": "9809326a225832f541b9d3e70f176135", 
            "weight": 2
        }, 
        {
            "AST Diff": 0, 
            "Profile Diff": false, 
            "id": "('test/unit/test_config.py', '(func:8585:(ined:8621))')", 
            "md5": "3526298a4457c1dcb8edc31c970ff8e0", 
            "weight": 2
        }, 
        {
            "AST Diff": 0, 
            "Profile Diff": false, 
            "id": "('src/gofer/mp.py', '(func:4142:(__init__:4146))')", 
            "md5": "17cb83c5adbd2eae4fc8ab4865880f4e", 
            "weight": 2
        }, 
        {
            "AST Diff": 0, 
            "Profile Diff": false, 
            "id": "('test/unit/test_collator.py', '(func:3790:(test_function:3827))')", 
            "md5": "5e63e5429314d9ea2541f360f7579561", 
            "weight": 2
        }, 
        {
            "AST Diff": 0, 
            "Profile Diff": false, 
            "id": "('test/unit/test_config.py', '(func:14853:(test_repr:14857))')", 
            "md5": "97da1f1b86d92760fb8c352e95c95190", 
            "weight": 2
        }, 
        {
            "AST Diff": 0, 
            "Profile Diff": false, 
            "id": "('test/unit/test_mp.py', '(func:5972:(test_eof:5976))')", 
            "md5": "da34b84fdbac080633c910bdb5dd2b66", 
            "weight": 2
        }, 
        {
            "AST Diff": 0, 
            "Profile Diff": false, 
            "id": "('src/gofer/config.py', '(func:15640:(__new__:15644))')", 
            "md5": "7418e0081a54c627ca14bc6b5aa0c8e6", 
            "weight": 2
        }, 
        {
            "AST Diff": 0, 
            "Profile Diff": false, 
            "id": "('test/unit/test_mp.py', '(func:4404:(test_enter:4443))')", 
            "md5": "ad07a1dd95202183bd959e58af5dd41a", 
            "weight": 2
        }, 
        {
            "AST Diff": 0, 
            "Profile Diff": false, 
            "id": "('test/unit/test_config.py', '(func:7276:(test_validate:7317))')", 
            "md5": "4a88d240d7be8830806ecb20988c04b1", 
            "weight": 2
        }, 
        {
            "AST Diff": 0, 
            "Profile Diff": false, 
            "id": "('test/unit/test_common.py', '(func:1226:(__init__:1230))')", 
            "md5": "4b59c2724a86127577144392ff5a8850", 
            "weight": 2
        }, 
        {
            "AST Diff": 0, 
            "Profile Diff": false, 
            "id": "('test/unit/test_common.py', '(func:6253:(test_abort:6257))')", 
            "md5": "e8cd8f0bf553b5cdb3314185144a40ac", 
            "weight": 2
        }, 
        {
            "AST Diff": 0, 
            "Profile Diff": false, 
            "id": "('test/unit/test_config.py', '(func:15534:(test_strict_get:15538))')", 
            "md5": "a4ae359039b6efe4a28b97af22e8ed7b", 
            "weight": 2
        }, 
        {
            "AST Diff": 0, 
            "Profile Diff": false, 
            "id": "('src/gofer/config.py', '(func:18118:(read:18122))')", 
            "md5": "f9ad9dd628b4e5ad592afa65b35fe08c", 
            "weight": 2
        }, 
        {
            "AST Diff": 0, 
            "Profile Diff": false, 
            "id": "('test/unit/test_common.py', '(func:4899:(test_synchronized:4903))')", 
            "md5": "66993a435ad151b367a746e15b29723d", 
            "weight": 2
        }, 
        {
            "AST Diff": 0, 
            "Profile Diff": false, 
            "id": "('src/gofer/common.py', '(func:3475:(sfn:3479))')", 
            "md5": "ea4c4662496e8ac38be97f36b703d24b", 
            "weight": 2
        }, 
        {
            "AST Diff": 0, 
            "Profile Diff": false, 
            "id": "('test/unit/test_config.py', '(func:18581:(test_iread:18616))')", 
            "md5": "7dba54f4364c6fca036b16266e3210fd", 
            "weight": 2
        }, 
        {
            "AST Diff": 0, 
            "Profile Diff": false, 
            "id": "('src/gofer/mp.py', '(func:3172:(put:3176))')", 
            "md5": "65d146c99ae7e0f7e3dd9f8f35177314", 
            "weight": 2
        }, 
        {
            "AST Diff": 0, 
            "Profile Diff": false, 
            "id": "('test/unit/test_config.py', '(func:7507:(test_setitem:7511))')", 
            "md5": "184873b4ccaeaad847298c419bd99962", 
            "weight": 2
        }, 
        {
            "AST Diff": 0, 
            "Profile Diff": false, 
            "id": "('src/gofer/config.py', '(func:16578:(read:16582))')", 
            "md5": "d6ea24d17ef9ea955f8a3ab6a9d9fcb0", 
            "weight": 2
        }, 
        {
            "AST Diff": 0, 
            "Profile Diff": false, 
            "id": "('test/unit/test_metrics.py', '(func:5362:(test_sizeof_not_formatted:5366))')", 
            "md5": "baab25d61a01fdf854fdec254d50f30a", 
            "weight": 2
        }, 
        {
            "AST Diff": 0, 
            "Profile Diff": false, 
            "id": "('src/gofer/common.py', '(func:4351:(__init__:4355))')", 
            "md5": "91dfcc2a7b08b1ca411b40b060ab0d23", 
            "weight": 2
        }, 
        {
            "AST Diff": 0, 
            "Profile Diff": false, 
            "id": "('src/gofer/common.py', '(func:2122:(aborted:2144))')", 
            "md5": "fdf4f891234127c70b5a4601965e50c1", 
            "weight": 2
        }, 
        {
            "AST Diff": 0, 
            "Profile Diff": false, 
            "id": "('src/gofer/config.py', '(func:8331:(__init__:8335))')", 
            "md5": "6f06bc0c587241cf9c3222e7ee753c1d", 
            "weight": 2
        }, 
        {
            "AST Diff": 0, 
            "Profile Diff": false, 
            "id": "('src/gofer/config.py', '(func:19315:(split:19337))')", 
            "md5": "47d3f1534863cd857c40e867e0d17ec2", 
            "weight": 2
        }, 
        {
            "AST Diff": 0, 
            "Profile Diff": false, 
            "id": "('src/gofer/collator.py', '__eq__:118')", 
            "md5": "18830a1fc9571f039d93e29206cca714", 
            "weight": 2
        }, 
        {
            "AST Diff": 0, 
            "Profile Diff": false, 
            "id": "('test/unit/test_config.py', '(func:4574:(test_property_not_valid:4578))')", 
            "md5": "eade6627ec22bde30d79dd86d5fa4af6", 
            "weight": 2
        }, 
        {
            "AST Diff": 0, 
            "Profile Diff": false, 
            "id": "('src/gofer/common.py', '(func:4578:(__getitem__:4582))')", 
            "md5": "0b50fb21318d6ae67850726e32406a13", 
            "weight": 2
        }, 
        {
            "AST Diff": 0, 
            "Profile Diff": false, 
            "id": "('test/unit/test_collator.py', '(func:816:(test_init:820))')", 
            "md5": "0d7bf57a94733c2fb89835c6d8a25703", 
            "weight": 2
        }, 
        {
            "AST Diff": 0, 
            "Profile Diff": false, 
            "id": "('test/unit/test_config.py', '(func:11327:(test_validate:11381))')", 
            "md5": "554cf2b1c09d3f1de24991d72013ff4a", 
            "weight": 2
        }, 
        {
            "AST Diff": 0, 
            "Profile Diff": false, 
            "id": "('test/unit/test_config.py', '(func:11847:(test_valid_property:11896))')", 
            "md5": "0d21aa63eb35e0d2287d54dac28206d4", 
            "weight": 2
        }, 
        {
            "AST Diff": 0, 
            "Profile Diff": false, 
            "id": "('test/unit/test_mp.py', '(func:1558:(test_start_parent:1620))')", 
            "md5": "4a40ba0e06dbd6d3ce099de937ebd439", 
            "weight": 2
        }, 
        {
            "AST Diff": 0, 
            "Profile Diff": false, 
            "id": "('test/unit/test_mp.py', '(func:4961:(test_close:4988))')", 
            "md5": "80d8e8343e88096f2d535b68e91933cc", 
            "weight": 2
        }, 
        {
            "AST Diff": 0, 
            "Profile Diff": false, 
            "id": "('test/unit/test_config.py', '(func:6845:(test_graph:6882))')", 
            "md5": "bf486c90f571bc48743913e0ef0c945e", 
            "weight": 2
        }, 
        {
            "AST Diff": 0, 
            "Profile Diff": false, 
            "id": "('test/unit/test_common.py', '(func:7254:(test_repr:7258))')", 
            "md5": "074bb122df34d0c3923084ea81941d15", 
            "weight": 2
        }, 
        {
            "AST Diff": 0, 
            "Profile Diff": false, 
            "id": "('test/unit/test_collator.py', '(func:1016:(test_collate:1132))')", 
            "md5": "3bf5335aeb05af9d99d5e7b798de940e", 
            "weight": 2
        }, 
        {
            "AST Diff": 0, 
            "Profile Diff": false, 
            "id": "('test/unit/test_metrics.py', '(func:4359:(test_sizeof_dict:4363))')", 
            "md5": "3468427389b166c4a1eb2ccffdd58e19", 
            "weight": 2
        }, 
        {
            "AST Diff": 0, 
            "Profile Diff": false, 
            "id": "('src/gofer/config.py', '(func:8974:(undefined:8978))')", 
            "md5": "e2a63bd05684ccf7fc8c4b6d66778e68", 
            "weight": 2
        }, 
        {
            "AST Diff": 0, 
            "Profile Diff": false, 
            "id": "('src/gofer/mp.py', '(func:2787:(poll:2791))')", 
            "md5": "f8b8c9d420d185ae47528f25898c899b", 
            "weight": 2
        }, 
        {
            "AST Diff": 0, 
            "Profile Diff": false, 
            "id": "('src/gofer/mp.py', '(func:2514:(__init__:2518))')", 
            "md5": "5d5c38a0a83e66cc5ee5beda20ba393b", 
            "weight": 2
        }, 
        {
            "AST Diff": 0, 
            "Profile Diff": false, 
            "id": "('test/unit/test_collator.py', '(func:3019:(test_classes:3053))')", 
            "md5": "f69f5924fb5a1293402325f36e1eb2a5", 
            "weight": 2
        }, 
        {
            "AST Diff": 0, 
            "Profile Diff": false, 
            "id": "('test/unit/test_config.py', '(func:19295:(test_jread:19330))')", 
            "md5": "52c6c5760abe81a22005d7e7ea19fb05", 
            "weight": 2
        }, 
        {
            "AST Diff": 0, 
            "Profile Diff": false, 
            "id": "('src/gofer/common.py', '(func:5118:(__repr__:5122))')", 
            "md5": "5a55b56b469ed34a2ec72a8f6724cd82", 
            "weight": 2
        }, 
        {
            "AST Diff": 0, 
            "Profile Diff": false, 
            "id": "('src/gofer/metrics.py', '(func:3232:(format:3254))')", 
            "md5": "de742ecb566fb07dc6383873f64a3c52", 
            "weight": 2
        }, 
        {
            "AST Diff": 0, 
            "Profile Diff": false, 
            "id": "('src/gofer/config.py', '(func:3476:(__init__:3480))')", 
            "md5": "4c4c5923d150ab17787ac0552746d2b6", 
            "weight": 2
        }, 
        {
            "AST Diff": 0, 
            "Profile Diff": false, 
            "id": "('src/gofer/common.py', '(func:8176:(__unicode__:8180))')", 
            "md5": "2713663533c7ed534e3e3ecbb6be9d3e", 
            "weight": 2
        }, 
        {
            "AST Diff": 0, 
            "Profile Diff": false, 
            "id": "('src/gofer/mp.py', '(func:5077:(put:5081))')", 
            "md5": "e3a02e4cfb962383b27854f0325220b0", 
            "weight": 2
        }, 
        {
            "AST Diff": 0, 
            "Profile Diff": false, 
            "id": "('src/gofer/common.py', '(func:1826:(all:1848))')", 
            "md5": "ba55c2592078c384dcc3c7ce04562774", 
            "weight": 2
        }, 
        {
            "AST Diff": 0, 
            "Profile Diff": false, 
            "id": "('src/gofer/config.py', '(func:10886:(__lock:10908))')", 
            "md5": "1f902365ac8f37748852a71c02dcaf50", 
            "weight": 2
        }, 
        {
            "AST Diff": 0, 
            "Profile Diff": false, 
            "id": "('src/gofer/common.py', '(func:4125:(__init__:4129))')", 
            "md5": "324ed6e09c1996deebefe4196b486ffe", 
            "weight": 2
        }, 
        {
            "AST Diff": 0, 
            "Profile Diff": false, 
            "id": "('test/unit/test_metrics.py', '(func:2958:(test_context:2962))')", 
            "md5": "0572f8ecda790ffe7205375eaa99577d", 
            "weight": 2
        }, 
        {
            "AST Diff": 0, 
            "Profile Diff": false, 
            "id": "('src/gofer/config.py', '(func:2869:(__init__:2873))')", 
            "md5": "0b8036c001c271de5745768048f91e0e", 
            "weight": 2
        }, 
        {
            "AST Diff": 0, 
            "Profile Diff": false, 
            "id": "('src/gofer/mp.py', '(func:3638:(__init__:3642))')", 
            "md5": "8f2ca4ead486624e3fc15fff172cc55f", 
            "weight": 2
        }, 
        {
            "AST Diff": 0, 
            "Profile Diff": false, 
            "id": "('src/gofer/common.py', '(func:4478:(__setattr__:4482))')", 
            "md5": "5e71df9a51d5a674d15a52aacc8baf6f", 
            "weight": 2
        }, 
        {
            "AST Diff": 0, 
            "Profile Diff": false, 
            "id": "('test/unit/test_common.py', '(func:4320:(test_call_different_thread:4324))')", 
            "md5": "cab62fc25254bb2ce3360559f9200a63", 
            "weight": 2
        }, 
        {
            "AST Diff": 0, 
            "Profile Diff": false, 
            "id": "('src/gofer/common.py', '(func:936:(utf8:940))')", 
            "md5": "c566c61499f0e5de1b28df87922dd0e7", 
            "weight": 2
        }, 
        {
            "AST Diff": 0, 
            "Profile Diff": false, 
            "id": "('src/gofer/collator.py', 'collate:33')", 
            "md5": "bf3d78a0000530a19ea898da915497f4", 
            "weight": 2
        }, 
        {
            "AST Diff": 0, 
            "Profile Diff": false, 
            "id": "('test/unit/test_config.py', '(func:16282:(test_iter:16286))')", 
            "md5": "1680530dfccadaf1d458dd13b50d85af", 
            "weight": 2
        }, 
        {
            "AST Diff": 0, 
            "Profile Diff": false, 
            "id": "('src/gofer/config.py', '(func:3713:(__init__:3717))')", 
            "md5": "db94efac6e65ef32e5f35b8e1fa57465", 
            "weight": 2
        }, 
        {
            "AST Diff": 0, 
            "Profile Diff": false, 
            "id": "('src/gofer/mp.py', '(func:1237:(start:1241))')", 
            "md5": "4bc070ec1ec8e3c2978f69fa606b86f5", 
            "weight": 2
        }, 
        {
            "AST Diff": 0, 
            "Profile Diff": false, 
            "id": "('src/gofer/config.py', '(func:4761:(__init__:4765))')", 
            "md5": "63a31f346ddf11aacff276ba4e775700", 
            "weight": 2
        }, 
        {
            "AST Diff": 0, 
            "Profile Diff": false, 
            "id": "('src/gofer/common.py', '(func:4574:(__getattr__:4578))')", 
            "md5": "b87d0867417a29131c210b11616ed6f0", 
            "weight": 2
        }, 
        {
            "AST Diff": 0, 
            "Profile Diff": false, 
            "id": "('test/unit/test_common.py', '(func:2005:(test_call:2009))')", 
            "md5": "9fc8a68a33d5e1bf36c36cce7a99814a", 
            "weight": 2
        }, 
        {
            "AST Diff": 0, 
            "Profile Diff": false, 
            "id": "('test/unit/test_mp.py', '(func:1265:(test_start_child:1327))')", 
            "md5": "c92778a845da98e7ced22921ce3fbae7", 
            "weight": 2
        }, 
        {
            "AST Diff": 0, 
            "Profile Diff": false, 
            "id": "('test/unit/test_common.py', '(func:6554:(test_released:6605))')", 
            "md5": "c8ae805fa42f4fa6e32cc3090bb3faac", 
            "weight": 2
        }, 
        {
            "AST Diff": 0, 
            "Profile Diff": false, 
            "id": "('test/unit/test_common.py', '(func:834:(__init__:838))')", 
            "md5": "074b552194e174b28541ad623819fd1d", 
            "weight": 2
        }, 
        {
            "AST Diff": 0, 
            "Profile Diff": false, 
            "id": "('test/unit/test_decorators.py', '(func:1477:(test_secret:1519))')", 
            "md5": "df76feb7fd25d6f4e395768f9ed7937a", 
            "weight": 2
        }, 
        {
            "AST Diff": 0, 
            "Profile Diff": false, 
            "id": "('src/gofer/config.py', '(func:7746:(__setitem__:7750))')", 
            "md5": "376611c04abab13bb122bfa79f6939fa", 
            "weight": 2
        }, 
        {
            "AST Diff": 0, 
            "Profile Diff": false, 
            "id": "('test/unit/test_config.py', '(func:5469:(test_init:5592))')", 
            "md5": "cd8b20a4fe5e14ec8cda69c3e526e199", 
            "weight": 2
        }, 
        {
            "AST Diff": 0, 
            "Profile Diff": false, 
            "id": "('src/gofer/mp.py', '(func:3409:(__exit__:3413))')", 
            "md5": "343f95e6631712bfbe586ccfb0a68a08", 
            "weight": 2
        }, 
        {
            "AST Diff": 0, 
            "Profile Diff": false, 
            "id": "('src/gofer/config.py', '(func:6292:(update:6296))')", 
            "md5": "9aeb1dcc3f948648f60703af828ff321", 
            "weight": 2
        }, 
        {
            "AST Diff": 0, 
            "Profile Diff": false, 
            "id": "('test/unit/test_common.py', '(func:10044:(test_unicode:10048))')", 
            "md5": "cfc638284f5d9fb1c947c979dbbc407f", 
            "weight": 2
        }, 
        {
            "AST Diff": 0, 
            "Profile Diff": false, 
            "id": "('test/unit/test_config.py', '(func:16130:(test_repr:16134))')", 
            "md5": "1e2a50a0bc783caea5df5c0cb8ee66c0", 
            "weight": 2
        }, 
        {
            "AST Diff": 0, 
            "Profile Diff": false, 
            "id": "('test/unit/test_config.py', '(func:17786:(test_read:17790))')", 
            "md5": "f1d8a27abdaed969e800361d21c46836", 
            "weight": 2
        }
    ]
}